odoo/addons/l10n_es_vat_book_oss/README.rst
odoo/addons/l10n_es_vat_book_oss/__init__.py
odoo/addons/l10n_es_vat_book_oss/__manifest__.py
odoo/addons/l10n_es_vat_book_oss/i18n/es.po
odoo/addons/l10n_es_vat_book_oss/i18n/l10n_es_vat_book_oss.pot
odoo/addons/l10n_es_vat_book_oss/models/__init__.py
odoo/addons/l10n_es_vat_book_oss/models/account_move.py
odoo/addons/l10n_es_vat_book_oss/models/aeat_vat_book_map_lines.py
odoo/addons/l10n_es_vat_book_oss/readme/CONFIGURE.md
odoo/addons/l10n_es_vat_book_oss/readme/CONTRIBUTORS.md
odoo/addons/l10n_es_vat_book_oss/readme/DESCRIPTION.md
odoo/addons/l10n_es_vat_book_oss/readme/INSTALL.md
odoo/addons/l10n_es_vat_book_oss/readme/USAGE.md
odoo/addons/l10n_es_vat_book_oss/static/description/icon.png
odoo/addons/l10n_es_vat_book_oss/static/description/index.html
odoo/addons/l10n_es_vat_book_oss/tests/__init__.py
odoo/addons/l10n_es_vat_book_oss/tests/test_l10n_es_aeat_vat_book_oss.py
odoo_addon_l10n_es_vat_book_oss-18.0.1.0.1.1.dist-info/METADATA
odoo_addon_l10n_es_vat_book_oss-18.0.1.0.1.1.dist-info/WHEEL
odoo_addon_l10n_es_vat_book_oss-18.0.1.0.1.1.dist-info/top_level.txt
odoo_addon_l10n_es_vat_book_oss-18.0.1.0.1.1.dist-info/RECORD
